django_admin_custom_filters/__init__.py
django_admin_custom_filters/admin.py
django_admin_custom_filters/filters.py
django_admin_custom_filters/templatetags/__init__.py
django_admin_custom_filters/templatetags/extras.py
django_admin_custom_filters-0.1.0.dist-info/LICENSE
django_admin_custom_filters-0.1.0.dist-info/METADATA
django_admin_custom_filters-0.1.0.dist-info/WHEEL
django_admin_custom_filters-0.1.0.dist-info/top_level.txt
django_admin_custom_filters-0.1.0.dist-info/RECORD
