Metadata-Version: 2.1
Name: django-admin-custom-filters
Version: 0.1.0
Summary: Custom filters for Django Admin
Home-page: https://github.com/StelosHight/django_admin_custom_filters
Author: StelosHight
Author-email: stanislav.khansu@gmail.com
License: GPL
Platform: UNKNOWN
Classifier: Development Status :: 4 - Beta
Classifier: License :: OSI Approved :: GNU General Public License v3 (GPLv3)
Classifier: Operating System :: POSIX :: Linux
Classifier: Programming Language :: Python :: 3.6
Classifier: Programming Language :: Python :: 3.7
Classifier: Programming Language :: Python :: 3.8
Requires-Python: >=3.6
Requires-Dist: Django (<3.0.4,>=2.1.2)
